lemon/__init__.py
lemon/api.py
lemon/base.py
lemon/errors.py
lemon/types.py
lemon/market_data/__init__.py
lemon/market_data/api.py
lemon/market_data/instruments.py
lemon/market_data/ohlc.py
lemon/market_data/quotes.py
lemon/market_data/trades.py
lemon/market_data/venues.py
lemon/market_data/model/__init__.py
lemon/market_data/model/instrument.py
lemon/market_data/model/ohlc.py
lemon/market_data/model/quote.py
lemon/market_data/model/trade.py
lemon/market_data/model/venue.py
lemon/streaming/__init__.py
lemon/streaming/api.py
lemon/streaming/model/__init__.py
lemon/streaming/model/authenticate.py
lemon/trading/__init__.py
lemon/trading/account.py
lemon/trading/api.py
lemon/trading/orders.py
lemon/trading/positions.py
lemon/trading/user.py
lemon/trading/model/__init__.py
lemon/trading/model/account.py
lemon/trading/model/order.py
lemon/trading/model/position.py
lemon/trading/model/user.py
lemon-1.3.1.dist-info/LICENSE
lemon-1.3.1.dist-info/WHEEL
lemon-1.3.1.dist-info/METADATA
lemon-1.3.1.dist-info/RECORD
