Metadata-Version: 2.1
Name: lemon
Version: 1.3.1
Summary: Official Python client for lemon.markets API
Author-email: "lemon.markets" <support@lemon.markets>
Requires-Python: >=3.7,<4
Classifier: Development Status :: 5 - Production/Stable
Classifier: Intended Audience :: Developers
Classifier: License :: OSI Approved :: MIT License
Classifier: Natural Language :: English
Classifier: Operating System :: OS Independent
Classifier: Programming Language :: Python
Classifier: Programming Language :: Python :: 3
Classifier: Programming Language :: Python :: 3.7
Classifier: Programming Language :: Python :: 3.8
Classifier: Programming Language :: Python :: 3.9
Classifier: Programming Language :: Python :: 3.10
Classifier: Programming Language :: Python :: 3.11
Classifier: Programming Language :: Python :: 3 :: Only
Classifier: Programming Language :: Python :: Implementation :: CPython
Classifier: Topic :: Internet :: WWW/HTTP
Classifier: Topic :: Software Development :: Libraries
Requires-Dist: pytz>=2022.1
Requires-Dist: requests>=2.27.1
Requires-Dist: typing-extensions>=4.2.0
Requires-Dist: urllib3>=1.26.0,<2
Requires-Dist: autoflake ; extra == "dev"
Requires-Dist: black ; extra == "dev"
Requires-Dist: isort ; extra == "dev"
Requires-Dist: mypy ; extra == "dev"
Requires-Dist: mypy-extensions ; extra == "dev"
Requires-Dist: pylint ; extra == "dev"
Requires-Dist: types-requests ; extra == "dev"
Requires-Dist: types-pytz ; extra == "dev"
Requires-Dist: pytest ; extra == "test"
Requires-Dist: pytest-cov ; extra == "test"
Requires-Dist: pytest-dotenv ; extra == "test"
Requires-Dist: pytest_httpserver ; extra == "test"
Project-URL: Changes, https://github.com/lemon-markets/sdk-python/blob/master/CHANGELOG.md
Project-URL: Documentation, https://docs.lemon.markets/
Project-URL: Download, https://pypi.python.org/pypi/lemon/
Project-URL: Home, https://www.lemon.markets/
Project-URL: Source, https://github.com/lemon-markets/sdk-python/
Project-URL: Tracker, https://github.com/lemon-markets/sdk-python/issues/
Provides-Extra: dev
Provides-Extra: test
